aiomeasures/__init__.py
aiomeasures-0.6.dist-info/METADATA
aiomeasures-0.6.dist-info/WHEEL
aiomeasures-0.6.dist-info/top_level.txt
aiomeasures-0.6.dist-info/RECORD
