Metadata-Version: 2.1
Name: aiomeasures
Version: 0.6
Summary: Squatted pypi package
Home-page: http://lab.errorist.xyz/abc/
Author: Xavier Barbosa
Author-email: clint.northwood@gmail.com
License: UNKNOWN
Platform: UNKNOWN
Classifier: Development Status :: 7 - Inactive
